plasma/__init__.py
plasma/colormap.py
plasma/methods.py
plotly_plasma-0.2.1.dist-info/METADATA
plotly_plasma-0.2.1.dist-info/WHEEL
plotly_plasma-0.2.1.dist-info/top_level.txt
plotly_plasma-0.2.1.dist-info/RECORD
