Metadata-Version: 2.1
Name: plotly-plasma
Version: 0.2.1
Summary: A small opinionated enhancement for Plotly
Home-page: https://github.com/a0th/plotly
Author: Nilo Araujo
Author-email: renard.agne@gmail.com
License: UNKNOWN
Platform: UNKNOWN
Requires-Dist: pandas (>=1.0.0)
Requires-Dist: plotly (>=5.0.0)
